__init__.py
base_redis_state_model.py
config.py
redis_client.py
pydantic_state_manager-0.1.0.dist-info/licenses/LICENCE
pydantic_state_manager-0.1.0.dist-info/METADATA
pydantic_state_manager-0.1.0.dist-info/WHEEL
pydantic_state_manager-0.1.0.dist-info/top_level.txt
pydantic_state_manager-0.1.0.dist-info/RECORD
