Metadata-Version: 2.4
Name: pydantic-state-manager
Version: 0.1.0
Summary: Add your description here
Requires-Python: >=3.13
License-File: LICENCE
Requires-Dist: pydantic-settings>=2.9.1
Requires-Dist: pydantic>=2.11.3
Requires-Dist: redis>=5.2.1
Dynamic: license-file
